ubpe_native/__init__.py
ubpe_native/ubpe.py
ubpe_native/ubpe_base.py
ubpe_native/ubpe_classic.py
ubpe_native/utils/__init__.py
ubpe_native/utils/pair_counter.py
ubpe_native/utils/ssstree.py
ubpe_native/utils/top_elements.py
ubpe_native/utils/utils.py
ubpe_native-0.2.3.dist-info/METADATA
ubpe_native-0.2.3.dist-info/WHEEL
ubpe_native-0.2.3.dist-info/licenses/LICENSE
ubpe_native-0.2.3.dist-info/RECORD
