Metadata-Version: 2.4
Name: ubpe-native
Version: 0.2.3
Summary: Python implementation of UBPE tokenization algorithm.
License-File: LICENSE
Author: Scurrra (Ilja Baroŭski)
Author-email: iscurrra@gmail.com
Requires-Python: >=3.12
Classifier: Programming Language :: Python :: 3
Classifier: Development Status :: 4 - Beta
Classifier: Programming Language :: Python :: Implementation
Project-URL: Issues, https://github.com/Scurrra/ubpe-native/issues
Project-URL: Repository, https://github.com/Scurrra/ubpe-native.git
